pygaze/__init__.py
pygaze/defaults.py
pygaze/display.py
pygaze/eyetracker.py
pygaze/joystick.py
pygaze/keyboard.py
pygaze/libgazecon.py
pygaze/libinput.py
pygaze/liblog.py
pygaze/libscreen.py
pygaze/libsound.py
pygaze/libtime.py
pygaze/logfile.py
pygaze/mouse.py
pygaze/py3compat.py
pygaze/screen.py
pygaze/settings.py
pygaze/sound.py
pygaze/time.py
pygaze/_display/__init__.py
pygaze/_display/basedisplay.py
pygaze/_display/osdisplay.py
pygaze/_display/psychopydisplay.py
pygaze/_display/pygamedisplay.py
pygaze/_eyetracker/__init__.py
pygaze/_eyetracker/baseeyetracker.py
pygaze/_eyetracker/eyelinkgraphics.py
pygaze/_eyetracker/iViewXAPI.py
pygaze/_eyetracker/libalea.py
pygaze/_eyetracker/libdumbdummy.py
pygaze/_eyetracker/libdummytracker.py
pygaze/_eyetracker/libeyelink.py
pygaze/_eyetracker/libeyelogic.py
pygaze/_eyetracker/libeyetribe.py
pygaze/_eyetracker/libopengaze.py
pygaze/_eyetracker/libsmi.py
pygaze/_eyetracker/libtobii.py
pygaze/_eyetracker/libtobiiglasses.py
pygaze/_eyetracker/libtobiilegacy.py
pygaze/_eyetracker/opengaze.py
pygaze/_eyetracker/pytribe.py
pygaze/_eyetracker/alea/CEtAPI.dll
pygaze/_eyetracker/alea/CEtAPIx64.dll
pygaze/_eyetracker/alea/EtApi.dll
pygaze/_eyetracker/alea/LICENSE
pygaze/_eyetracker/alea/README.md
pygaze/_eyetracker/alea/__init__.py
pygaze/_eyetracker/alea/alea.py
pygaze/_eyetracker/eyelogic/ELApi.dll
pygaze/_eyetracker/eyelogic/ELApi.py
pygaze/_eyetracker/eyelogic/ELApi32.dll
pygaze/_eyetracker/eyelogic/ELCApi.dll
pygaze/_eyetracker/eyelogic/ELCApi32.dll
pygaze/_eyetracker/eyelogic/__init__.py
pygaze/_eyetracker/eyelogic/concrt140.dll
pygaze/_eyetracker/eyelogic/msvcp140.dll
pygaze/_eyetracker/eyelogic/msvcp140_1.dll
pygaze/_eyetracker/eyelogic/msvcp140_2.dll
pygaze/_eyetracker/eyelogic/vccorlib140.dll
pygaze/_eyetracker/eyelogic/vcruntime140.dll
pygaze/_eyetracker/tobiiglasses/__init__.py
pygaze/_eyetracker/tobiiglasses/tobiiglassescontroller.py
pygaze/_joystick/__init__.py
pygaze/_joystick/basejoystick.py
python_pygaze-0.7.6.dist-info/COPYING.txt
python_pygaze-0.7.6.dist-info/METADATA
python_pygaze-0.7.6.dist-info/WHEEL
python_pygaze-0.7.6.dist-info/top_level.txt
python_pygaze-0.7.6.dist-info/RECORD
