Metadata-Version: 2.1
Name: python-pygaze
Version: 0.7.6
Summary: A Python library for eye tracking
Home-page: https://www.pygaze.org/
Author: Edwin Dalmaijer
Author-email: edwin@dalmaijer.org
Classifier: Development Status :: 4 - Beta
Classifier: Intended Audience :: Science/Research
Classifier: Topic :: Scientific/Engineering
Classifier: Environment :: MacOS X
Classifier: Environment :: Win32 (MS Windows)
Classifier: Environment :: X11 Applications
Classifier: License :: OSI Approved :: GNU General Public License v3 or later (GPLv3+)
Classifier: Programming Language :: Python :: 3
Requires-Python: >=3
License-File: COPYING.txt
